pyKamipi/__init__.py
pyKamipi/pibot.py
pyKamipi/pibot_org.py
pyKamipi/robot_control.py
pykamipi-3.0.0.dist-info/METADATA
pykamipi-3.0.0.dist-info/WHEEL
pykamipi-3.0.0.dist-info/top_level.txt
pykamipi-3.0.0.dist-info/RECORD
