Metadata-Version: 2.4
Name: pyKamipi
Version: 3.0.0
Summary: A Python Library For Kamibot-Pi
Home-page: http://www.moyalab.com
Author: devdio
Author-email: kei.devdio@gmail.com
License: GNU GPLv3
Keywords: Kamibot Pi,KamibotPi,Robot
Classifier: Operating System :: Microsoft :: Windows
Classifier: Programming Language :: Python :: 3.10
Classifier: Programming Language :: Python :: 3.11
Classifier: Programming Language :: Python :: 3.12
Classifier: Topic :: Education
Requires-Python: >=3.10
Requires-Dist: termcolor
Requires-Dist: pyserial==3.5
Dynamic: author
Dynamic: author-email
Dynamic: classifier
Dynamic: description
Dynamic: description-content-type
Dynamic: home-page
Dynamic: keywords
Dynamic: license
Dynamic: requires-dist
Dynamic: requires-python
Dynamic: summary
